MANIFEST.in
README.md
setup.cfg
setup.py
versioneer.py
pokrok/__init__.py
pokrok/_version.py
pokrok/styles.py
pokrok.egg-info/PKG-INFO
pokrok.egg-info/SOURCES.txt
pokrok.egg-info/dependency_links.txt
pokrok.egg-info/entry_points.txt
pokrok.egg-info/top_level.txt
pokrok/plugins/__init__.py
pokrok/plugins/halo.py
pokrok/plugins/logging.py
pokrok/plugins/progressbar2.py
pokrok/plugins/tqdm.py