Metadata-Version: 1.1
Name: pokrok
Version: 0.2.0
Summary: Simple API for progress bars using any of several supported libraries
Home-page: https://github.com/jdidion/pokrok
Author: John Didion
Author-email: johndidion@gmail.com
License: MIT
Platform: UNKNOWN
Classifier: Development Status :: 3 - Alpha
Classifier: Environment :: Console
Classifier: Intended Audience :: Developers
Classifier: Topic :: Software Development :: User Interfaces
Classifier: License :: OSI Approved :: MIT License
Classifier: Natural Language :: English
Classifier: Programming Language :: Python :: 3
Classifier: Programming Language :: Python :: 3.4
Classifier: Programming Language :: Python :: 3.5
Classifier: Programming Language :: Python :: 3.6
